Metadata-Version: 2.2
Name: Topsis-Rohit-102203986
Version: 1.0.1
Summary: A Python package to perform TOPSIS analysis
Author: Rohit Deepchandani
Author-email: rohitdeepchandani@gmail.com
Classifier: Programming Language :: Python :: 3
Classifier: License :: OSI Approved :: MIT License
Classifier: Operating System :: OS Independent
Requires-Python: >=3.6
License-File: LICENSE
Requires-Dist: numpy
Requires-Dist: pandas
Dynamic: author
Dynamic: author-email
Dynamic: classifier
Dynamic: description
Dynamic: description-content-type
Dynamic: requires-dist
Dynamic: requires-python
Dynamic: summary
